simplepacker/__init__.py
simplepacker/algorithm.py
simplepacker/algorithm_greedy.py
simplepacker/files.py
simplepacker/geometry.py
simplepacker/settings.py
simplepacker/simplepacker.py
simplepacker/utility.py
simplepacker-0.2.dist-info/DESCRIPTION.rst
simplepacker-0.2.dist-info/METADATA
simplepacker-0.2.dist-info/RECORD
simplepacker-0.2.dist-info/WHEEL
simplepacker-0.2.dist-info/entry_points.txt
simplepacker-0.2.dist-info/metadata.json
simplepacker-0.2.dist-info/top_level.txt
tests/__init__.py
tests/common.py
tests/test_basics.py
tests/test_files.py
tests/test_packing.py
